Metadata-Version: 2.1
Name: kicad-gitdiff
Version: 0.0.4
Summary: A tool for a visual diff with git and kicad
Home-page: https://github.com/maersdal/kicad_gitdiff_cli
Author: magnus ersdal
Author-email: magnus@resani.com
License: Apache-2.0
License-File: LICENSE
